[
  {
    "resultId": "12649314",
    "mail": "creche.aigues-vives@wanadoo.fr",
    "distance": 41368,
    "latitude": 43.7403223320883,
    "telephone": "0466353450",
    "statusCompte": 2,
    "type": "EAJE",
    "nom": "Multi-accueil\"Les Cigalous\"",
    "resultStructId": "3881",
    "omegaId": "0",
    "avip": false,
    "adresse": "rue jean mace 30670",
    "details": {
      "dispo": {
        "allNonRenseigne": true
      }
    },
    "derniereModifDate": "19/11/2023",
    "dispo": false,
    "longitude": 4.177373424991605,
    "ville": "aiguesvives",
    "cp": ""
  },
  {
    "resultId": "12649314",
    "mail": "creche.aigues-vives@wanadoo.fr",
    "distance": 438309,
    "latitude": 43.7403223320883,
    "telephone": "0466353450",
    "statusCompte": 2,
    "type": "EAJE",
    "nom": "Multi-accueil\"Les Cigalous\"",
    "resultStructId": "3881",
    "omegaId": "0",
    "avip": false,
    "adresse": "rue jean mace 30670",
    "details": {
      "dispo": {
        "allNonRenseigne": true
      }
    },
    "derniereModifDate": "19/11/2023",
    "dispo": false,
    "longitude": 4.177373424991605,
    "ville": "aiguesvives",
    "cp": ""
  },
  {
    "resultId": "12649314",
    "mail": "creche.aigues-vives@wanadoo.fr",
    "distance": 27527,
    "latitude": 43.7403223320883,
    "telephone": "0466353450",
    "statusCompte": 2,
    "type": "EAJE",
    "nom": "Multi-accueil\"Les Cigalous\"",
    "resultStructId": "3881",
    "omegaId": "0",
    "avip": false,
    "adresse": "rue jean mace 30670",
    "details": {
      "dispo": {
        "allNonRenseigne": true
      }
    },
    "derniereModifDate": "19/11/2023",
    "dispo": false,
    "longitude": 4.177373424991605,
    "ville": "aiguesvives",
    "cp": ""
  },
  {
    "resultId": "12649314",
    "mail": "creche.aigues-vives@wanadoo.fr",
    "distance": 153050,
    "latitude": 43.7403223320883,
    "telephone": "0466353450",
    "statusCompte": 2,
    "type": "EAJE",
    "nom": "Multi-accueil\"Les Cigalous\"",
    "resultStructId": "3881",
    "omegaId": "0",
    "avip": false,
    "adresse": "rue jean mace 30670",
    "details": {
      "dispo": {
        "allNonRenseigne": true
      }
    },
    "derniereModifDate": "19/11/2023",
    "dispo": false,
    "longitude": 4.177373424991605,
    "ville": "aiguesvives",
    "cp": ""
  }
]