[
  {
    "resultId": "12590963",
    "mail": "ccapucine82@gmail.com",
    "distance": 158433,
    "latitude": 44.14993376071487,
    "telephone": "0563682273",
    "statusCompte": 2,
    "type": "EAJE",
    "nom": "EAJE- Capucine",
    "resultStructId": "675404",
    "omegaId": "0",
    "avip": false,
    "adresse": "route des fours a chaux 82140 st",
    "details": {
      "dispo": {
        "allNonRenseigne": true
      }
    },
    "derniereModifDate": "19/11/2023",
    "dispo": false,
    "longitude": 1.7327646988738208,
    "ville": "antoninnobleval",
    "cp": ""
  },
  {
    "resultId": "12590963",
    "mail": "ccapucine82@gmail.com",
    "distance": 183976,
    "latitude": 44.14993376071487,
    "telephone": "0563682273",
    "statusCompte": 2,
    "type": "EAJE",
    "nom": "EAJE- Capucine",
    "resultStructId": "675404",
    "omegaId": "0",
    "avip": false,
    "adresse": "route des fours a chaux 82140 st",
    "details": {
      "dispo": {
        "allNonRenseigne": true
      }
    },
    "derniereModifDate": "19/11/2023",
    "dispo": false,
    "longitude": 1.7327646988738208,
    "ville": "antoninnobleval",
    "cp": ""
  }
]