[
  {
    "resultId": "59543253",
    "mail": "lafenasse@creche-ma-deuxieme-maison.fr",
    "distance": 207544,
    "latitude": 43.76837894129107,
    "telephone": "0563557976",
    "statusCompte": 2,
    "type": "EAJE",
    "nom": "MICROCRECHE Familles Rurales Centre Tarn Lafenasse",
    "resultStructId": "698308",
    "omegaId": "0",
    "avip": false,
    "adresse": "12 bislotissement les fluorines 81120 terre",
    "details": {
      "dispo": {
        "allNonRenseigne": true
      }
    },
    "derniereModifDate": "19/11/2023",
    "dispo": false,
    "longitude": 2.232114416035526,
    "ville": "debancalie",
    "cp": ""
  },
  {
    "resultId": "59543253",
    "mail": "lafenasse@creche-ma-deuxieme-maison.fr",
    "distance": 135189,
    "latitude": 43.76837894129107,
    "telephone": "0563557976",
    "statusCompte": 2,
    "type": "EAJE",
    "nom": "MICROCRECHE Familles Rurales Centre Tarn Lafenasse",
    "resultStructId": "698308",
    "omegaId": "0",
    "avip": false,
    "adresse": "12 bislotissement les fluorines 81120 terre",
    "details": {
      "dispo": {
        "allNonRenseigne": true
      }
    },
    "derniereModifDate": "19/11/2023",
    "dispo": false,
    "longitude": 2.232114416035526,
    "ville": "debancalie",
    "cp": ""
  }
]