[
  {
    "resultId": "12591350",
    "mail": "crecheminiplume@gmail.com",
    "distance": 71640,
    "latitude": 44.98381799507028,
    "telephone": "0557641862",
    "statusCompte": 2,
    "type": "EAJE",
    "nom": "MiniPlume",
    "resultStructId": "694813",
    "omegaId": "0",
    "avip": false,
    "adresse": "315 route de compostelle 33240 la lande",
    "details": {
      "dispo": {
        "allNonRenseigne": true
      }
    },
    "derniereModifDate": "19/11/2023",
    "dispo": false,
    "longitude": -0.37679217981021956,
    "ville": "defronsac",
    "cp": ""
  }
]