[
  {
    "resultId": "12963497",
    "mail": "mc.autise@cc-vsa.com",
    "distance": 188078,
    "latitude": 46.47411776323309,
    "telephone": "0251500607",
    "statusCompte": 2,
    "type": "EAJE",
    "nom": "Micro-crècheintercommunale \"Les Pitchounes\"",
    "resultStructId": "11217",
    "omegaId": "0",
    "avip": false,
    "adresse": "4 rue du doue 85240 sthilaire",
    "details": {
      "dispo": {
        "allNonRenseigne": true
      }
    },
    "derniereModifDate": "19/11/2023",
    "dispo": false,
    "longitude": -0.662462322911123,
    "ville": "desloges",
    "cp": ""
  },
  {
    "resultId": "12963497",
    "mail": "mc.autise@cc-vsa.com",
    "distance": 129094,
    "latitude": 46.47411776323309,
    "telephone": "0251500607",
    "statusCompte": 2,
    "type": "EAJE",
    "nom": "Micro-crècheintercommunale \"Les Pitchounes\"",
    "resultStructId": "11217",
    "omegaId": "0",
    "avip": false,
    "adresse": "4 rue du doue 85240 sthilaire",
    "details": {
      "dispo": {
        "allNonRenseigne": true
      }
    },
    "derniereModifDate": "19/11/2023",
    "dispo": false,
    "longitude": -0.662462322911123,
    "ville": "desloges",
    "cp": ""
  },
  {
    "resultId": "12963497",
    "mail": "mc.autise@cc-vsa.com",
    "distance": 238816,
    "latitude": 46.47411776323309,
    "telephone": "0251500607",
    "statusCompte": 2,
    "type": "EAJE",
    "nom": "Micro-crècheintercommunale \"Les Pitchounes\"",
    "resultStructId": "11217",
    "omegaId": "0",
    "avip": false,
    "adresse": "4 rue du doue 85240 sthilaire",
    "details": {
      "dispo": {
        "allNonRenseigne": true
      }
    },
    "derniereModifDate": "19/11/2023",
    "dispo": false,
    "longitude": -0.662462322911123,
    "ville": "desloges",
    "cp": ""
  },
  {
    "resultId": "12963497",
    "mail": "mc.autise@cc-vsa.com",
    "distance": 129094,
    "latitude": 46.47411776323309,
    "telephone": "0251500607",
    "statusCompte": 2,
    "type": "EAJE",
    "nom": "Micro-crècheintercommunale \"Les Pitchounes\"",
    "resultStructId": "11217",
    "omegaId": "0",
    "avip": false,
    "adresse": "4 rue du doue 85240 sthilaire",
    "details": {
      "dispo": {
        "allNonRenseigne": true
      }
    },
    "derniereModifDate": "19/11/2023",
    "dispo": false,
    "longitude": -0.662462322911123,
    "ville": "desloges",
    "cp": ""
  }
]