[
  {
    "resultId": "40916160",
    "mail": "ma-lescanailles@lacali.fr",
    "distance": 57157,
    "latitude": 44.857718803534986,
    "telephone": "0557240797",
    "statusCompte": 2,
    "type": "EAJE",
    "nom": "Multi-accueilLes Canailles",
    "resultStructId": "690606",
    "omegaId": "0",
    "avip": false,
    "adresse": "4 route de libourne 33750 st germain",
    "details": {
      "dispo": {
        "allNonRenseigne": true
      }
    },
    "derniereModifDate": "19/11/2023",
    "dispo": false,
    "longitude": -0.32179547408154363,
    "ville": "dupuch",
    "cp": ""
  }
]