[
  {
    "resultId": "33514250",
    "mail": "hautscomme3pommes@yahoo.fr",
    "distance": 147556,
    "latitude": 47.54966755934381,
    "telephone": "0671991063",
    "statusCompte": 2,
    "type": "EAJE",
    "nom": "Micro-crècheprivée Hauts comme 3 pommes, Baugé en Anjou",
    "resultStructId": "709743",
    "omegaId": "0",
    "avip": false,
    "adresse": "10 avenuede la pree 49150 bauge",
    "details": {
      "dispo": {
        "allNonRenseigne": true
      }
    },
    "derniereModifDate": "19/11/2023",
    "dispo": false,
    "longitude": -0.10046800947088334,
    "ville": "enanjou",
    "cp": ""
  },
  {
    "resultId": "12950554",
    "mail": "crechefamiliale@association-galipette.org",
    "distance": 147578,
    "latitude": 47.54379778954025,
    "telephone": "0241892185",
    "statusCompte": 2,
    "type": "EAJE",
    "nom": "Crèchefamiliale associative \"La Galipette\" Baugé",
    "resultStructId": "688810",
    "omegaId": "0",
    "avip": false,
    "adresse": "8 bis ruede la croix verte 49150 bauge",
    "details": {
      "dispo": {
        "allNonRenseigne": true
      }
    },
    "derniereModifDate": "19/11/2023",
    "dispo": false,
    "longitude": -0.10457289074768139,
    "ville": "enanjou",
    "cp": ""
  },
  {
    "resultId": "12929613",
    "mail": "creche@association-galipette.org",
    "distance": 147578,
    "latitude": 47.54379778954025,
    "telephone": "0241897750",
    "statusCompte": 2,
    "type": "EAJE",
    "nom": "Multi-accueilla \"Galipette\", Baugé en Anjou",
    "resultStructId": "695501",
    "omegaId": "0",
    "avip": false,
    "adresse": "8 bis rue de la croixverte 49150 bauge",
    "details": {
      "dispo": {
        "allNonRenseigne": true
      }
    },
    "derniereModifDate": "19/11/2023",
    "dispo": false,
    "longitude": -0.10457289074768139,
    "ville": "enanjou",
    "cp": ""
  },
  {
    "resultId": "13016645",
    "mail": "multi-accueil@doue-en-anjou.fr",
    "distance": 150163,
    "latitude": 47.198959111337714,
    "telephone": "0241597698",
    "statusCompte": 2,
    "type": "EAJE",
    "nom": "Multi-accueilmunicipal de Doué-en-Anjou",
    "resultStructId": "639301",
    "omegaId": "0",
    "avip": false,
    "adresse": "4 rue pasteur 49700 doue",
    "details": {
      "dispo": {
        "allNonRenseigne": true
      }
    },
    "derniereModifDate": "19/11/2023",
    "dispo": false,
    "longitude": -0.2810753492708722,
    "ville": "enanjou",
    "cp": ""
  },
  {
    "resultId": "12929484",
    "mail": "lesgaiminous@beaufortenanjou.fr",
    "distance": 151574,
    "latitude": 47.44037949351048,
    "telephone": "0241444431",
    "statusCompte": 2,
    "type": "EAJE",
    "nom": "Halte-garderieAFR \"Les Gaiminous\", Beaufort en Vallée",
    "resultStructId": "701448",
    "omegaId": "0",
    "avip": false,
    "adresse": "1 rue desdeportes 49250 beaufort",
    "details": {
      "dispo": {
        "allNonRenseigne": true
      }
    },
    "derniereModifDate": "19/11/2023",
    "dispo": false,
    "longitude": -0.2191919265895991,
    "ville": "enanjou",
    "cp": ""
  },
  {
    "resultId": "59872469",
    "mail": "contact@dansmacabane.fr",
    "distance": 153369,
    "latitude": 47.43951129787905,
    "telephone": "0672988581",
    "statusCompte": 2,
    "type": "EAJE",
    "nom": "Micro-crèchesprivées Dans ma Cabane 2, Beaufort en Anjou",
    "resultStructId": "709786",
    "omegaId": "0",
    "avip": false,
    "adresse": "14 route del'izenelle 49250 beaufort",
    "details": {
      "dispo": {
        "allNonRenseigne": true
      }
    },
    "derniereModifDate": "19/11/2023",
    "dispo": false,
    "longitude": -0.24468319711073766,
    "ville": "enanjou",
    "cp": ""
  },
  {
    "resultId": "57948239",
    "mail": "contact@dansmacabane.fr",
    "distance": 153523,
    "latitude": 47.44595097044252,
    "telephone": "0672988581",
    "statusCompte": 2,
    "type": "EAJE",
    "nom": "Micro-crèchesprivées Dans ma Cabane 1, Beaufort en Anjou",
    "resultStructId": "709787",
    "omegaId": "0",
    "avip": false,
    "adresse": "22 rue deshauts champs 49250 beaufort",
    "details": {
      "dispo": {
        "allNonRenseigne": true
      }
    },
    "derniereModifDate": "19/11/2023",
    "dispo": false,
    "longitude": -0.24376703520258264,
    "ville": "enanjou",
    "cp": ""
  },
  {
    "resultId": "13037207",
    "mail": "multiaccueil.petitpoucet@gmail.com",
    "distance": 170105,
    "latitude": 47.522543871750294,
    "telephone": "0241764690",
    "statusCompte": 2,
    "type": "EAJE",
    "nom": "Multi-accueil\"Petit Poucet\", Pellouailles les vignes",
    "resultStructId": "23817",
    "omegaId": "0",
    "avip": false,
    "adresse": "13 rue desvignes 49112 verrieres",
    "details": {
      "dispo": {
        "allNonRenseigne": true
      }
    },
    "derniereModifDate": "19/11/2023",
    "dispo": false,
    "longitude": -0.4384959073285132,
    "ville": "enanjou",
    "cp": ""
  },
  {
    "resultId": "13037594",
    "mail": "multiaccueil.grainsdesoleil@gmail.com",
    "distance": 172134,
    "latitude": 47.51917916128481,
    "telephone": "0241768937",
    "statusCompte": 2,
    "type": "EAJE",
    "nom": "Multi-accueil\"Grains de Soleil\", Saint Sylvain d'Anjou",
    "resultStructId": "713602",
    "omegaId": "0",
    "avip": false,
    "adresse": "1 rue desbles d'or 49480 verrieres",
    "details": {
      "dispo": {
        "allNonRenseigne": true
      }
    },
    "derniereModifDate": "19/11/2023",
    "dispo": false,
    "longitude": -0.46875914744586294,
    "ville": "enanjou",
    "cp": ""
  },
  {
    "resultId": "24775349",
    "mail": "picotietpicota@orange.fr",
    "distance": 172925,
    "latitude": 47.498032825446636,
    "telephone": "0241863427",
    "statusCompte": 2,
    "type": "EAJE",
    "nom": "Micro-crècheprivée Picoti et Picota, St Sylvain d'Anjou",
    "resultStructId": "709767",
    "omegaId": "0",
    "avip": false,
    "adresse": "5 chemin duclos dore 49480 verrieres",
    "details": {
      "dispo": {
        "allNonRenseigne": true
      }
    },
    "derniereModifDate": "19/11/2023",
    "dispo": false,
    "longitude": -0.4901402247050109,
    "ville": "enanjou",
    "cp": ""
  },
  {
    "resultId": "57823043",
    "mail": "marie@creche-poppins.fr",
    "distance": 172972,
    "latitude": 47.492031649951606,
    "telephone": "0632782428",
    "statusCompte": 2,
    "type": "EAJE",
    "nom": "Micro-crècheprivée Marie Poppins, St Sylvain d'Anjou",
    "resultStructId": "709738",
    "omegaId": "0",
    "avip": false,
    "adresse": "12 rue de lacharronnerie 49480 verrieres",
    "details": {
      "dispo": {
        "allNonRenseigne": true
      }
    },
    "derniereModifDate": "19/11/2023",
    "dispo": false,
    "longitude": -0.493618867924579,
    "ville": "enanjou",
    "cp": ""
  },
  {
    "resultId": "30287106",
    "mail": "1001petitesmains@orange.fr",
    "distance": 182899,
    "latitude": 47.241110538239916,
    "telephone": "0241300501",
    "statusCompte": 2,
    "type": "EAJE",
    "nom": "Micro-crècheprivée 1001 petites mains,Chemillé-en-Anjou",
    "resultStructId": "712502",
    "omegaId": "0",
    "avip": false,
    "allNonRenseigne": false,
    "adresse": "4 alleekonrad adenauer 49120 chemille",
    "details": {
      "dispo": {
        "allNonRenseigne": true
      }
    },
    "derniereModifDate": "19/11/2023",
    "dispo": false,
    "longitude": -0.7101051515314909,
    "ville": "enanjou",
    "cp": ""
  },
  {
    "resultId": "40256029",
    "mail": "micro-creche-au-pays-des-reves@orange.fr",
    "distance": 182901,
    "latitude": 47.24104967424489,
    "telephone": "0241627796",
    "statusCompte": 2,
    "type": "EAJE",
    "nom": "Micro-crècheprivée Au Pays des Rêves, Chemillé-en-Anjou",
    "resultStructId": "709717",
    "omegaId": "0",
    "avip": false,
    "adresse": "6 alleekonrad adenauer 49120 chemille",
    "details": {
      "dispo": {
        "allNonRenseigne": true
      }
    },
    "derniereModifDate": "19/11/2023",
    "dispo": false,
    "longitude": -0.7101390660477512,
    "ville": "enanjou",
    "cp": ""
  },
  {
    "resultId": "12930903",
    "mail": "ma-calinous-pdl@vyv3.fr",
    "distance": 183485,
    "latitude": 47.21391698397926,
    "telephone": "0241303922",
    "statusCompte": 2,
    "type": "EAJE",
    "nom": "Multi-accueil\"Les Calinous\", Chemillé - Chemillé en Anjou",
    "resultStructId": "713015",
    "omegaId": "0",
    "avip": false,
    "adresse": "4 bisrue la chesnaie 49120 chemille",
    "details": {
      "dispo": {
        "allNonRenseigne": true
      }
    },
    "derniereModifDate": "19/11/2023",
    "dispo": false,
    "longitude": -0.7228037056532637,
    "ville": "enanjou",
    "cp": ""
  },
  {
    "resultId": "24552604",
    "mail": "lacabanedescastors@gmail.com",
    "distance": 186865,
    "latitude": 47.52332826397502,
    "telephone": "0241951141",
    "statusCompte": 2,
    "type": "EAJE",
    "nom": "Micro-crècheprivée \"La Cabane des Castors\", La Meignanne",
    "resultStructId": "709762",
    "omegaId": "0",
    "avip": false,
    "adresse": "19 ruede la chenaie 49770 longuenee",
    "details": {
      "dispo": {
        "allNonRenseigne": true
      }
    },
    "derniereModifDate": "19/11/2023",
    "dispo": false,
    "longitude": -0.6729293981401675,
    "ville": "enanjou",
    "cp": ""
  },
  {
    "resultId": "12928108",
    "mail": "contact@lesptitspieds.fr",
    "distance": 188680,
    "latitude": 47.56041053686627,
    "telephone": "0629600084",
    "statusCompte": 2,
    "type": "EAJE",
    "nom": "Micro-crècheprivée Les P'tits Pieds, Longuenée-en-Anjou",
    "resultStructId": "709721",
    "omegaId": "0",
    "avip": false,
    "adresse": "38 rue paulgauguin 49770 longuenee",
    "details": {
      "dispo": {
        "allNonRenseigne": true
      }
    },
    "derniereModifDate": "19/11/2023",
    "dispo": false,
    "longitude": -0.6807524689792825,
    "ville": "enanjou",
    "cp": ""
  },
  {
    "resultId": "26377344",
    "mail": "crechedemelay@orange.fr",
    "distance": 193926,
    "latitude": 47.285711583583605,
    "telephone": "0241461851",
    "statusCompte": 2,
    "type": "EAJE",
    "nom": "Micro-crècheprivée Babychou, Melay",
    "resultStructId": "709723",
    "omegaId": "0",
    "avip": false,
    "adresse": "2 rue du haut des sources za dessources 49120 chemille",
    "details": {
      "dispo": {
        "allNonRenseigne": true
      }
    },
    "derniereModifDate": "19/11/2023",
    "dispo": false,
    "longitude": -0.848489419802517,
    "ville": "enanjou",
    "cp": ""
  },
  {
    "resultId": "57188989",
    "mail": "mademande@fazill-home.fr",
    "distance": 11136,
    "latitude": 47.60225745506025,
    "telephone": "0786829796",
    "statusCompte": 2,
    "type": "EAJE",
    "nom": "Micro-crècheprivée Fazill'home, Vernd'Anjou",
    "resultStructId": "709727",
    "omegaId": "0",
    "avip": false,
    "dateProchaineDispo": "2023-11-22",
    "adresse": "9 rue detatsfield 49220 erdre",
    "details": {
      "dispo": {
        "allNonRenseigne": true
      }
    },
    "derniereModifDate": "19/11/2023",
    "dispo": true,
    "longitude": -0.8325270663973513,
    "ville": "enanjou",
    "cp": ""
  },
  {
    "resultId": "12928108",
    "mail": "contact@lesptitspieds.fr",
    "distance": 23235,
    "latitude": 47.56041053686627,
    "telephone": "0629600084",
    "statusCompte": 2,
    "type": "EAJE",
    "nom": "Micro-crècheprivée Les P'tits Pieds, Longuenée-en-Anjou",
    "resultStructId": "709721",
    "omegaId": "0",
    "avip": false,
    "adresse": "38 rue paulgauguin 49770 longuenee",
    "details": {
      "dispo": {
        "allNonRenseigne": true
      }
    },
    "derniereModifDate": "19/11/2023",
    "dispo": false,
    "longitude": -0.6807524689792825,
    "ville": "enanjou",
    "cp": ""
  },
  {
    "resultId": "24552604",
    "mail": "lacabanedescastors@gmail.com",
    "distance": 25175,
    "latitude": 47.52332826397502,
    "telephone": "0241951141",
    "statusCompte": 2,
    "type": "EAJE",
    "nom": "Micro-crècheprivée \"La Cabane des Castors\", La Meignanne",
    "resultStructId": "709762",
    "omegaId": "0",
    "avip": false,
    "adresse": "19 ruede la chenaie 49770 longuenee",
    "details": {
      "dispo": {
        "allNonRenseigne": true
      }
    },
    "derniereModifDate": "19/11/2023",
    "dispo": false,
    "longitude": -0.6729293981401675,
    "ville": "enanjou",
    "cp": ""
  },
  {
    "resultId": "26377344",
    "mail": "crechedemelay@orange.fr",
    "distance": 37899,
    "latitude": 47.285711583583605,
    "telephone": "0241461851",
    "statusCompte": 2,
    "type": "EAJE",
    "nom": "Micro-crècheprivée Babychou, Melay",
    "resultStructId": "709723",
    "omegaId": "0",
    "avip": false,
    "adresse": "2 rue du haut des sources za dessources 49120 chemille",
    "details": {
      "dispo": {
        "allNonRenseigne": true
      }
    },
    "derniereModifDate": "19/11/2023",
    "dispo": false,
    "longitude": -0.848489419802517,
    "ville": "enanjou",
    "cp": ""
  },
  {
    "resultId": "57823043",
    "mail": "marie@creche-poppins.fr",
    "distance": 38962,
    "latitude": 47.492031649951606,
    "telephone": "0632782428",
    "statusCompte": 2,
    "type": "EAJE",
    "nom": "Micro-crècheprivée Marie Poppins, St Sylvain d'Anjou",
    "resultStructId": "709738",
    "omegaId": "0",
    "avip": false,
    "adresse": "12 rue de lacharronnerie 49480 verrieres",
    "details": {
      "dispo": {
        "allNonRenseigne": true
      }
    },
    "derniereModifDate": "19/11/2023",
    "dispo": false,
    "longitude": -0.493618867924579,
    "ville": "enanjou",
    "cp": ""
  },
  {
    "resultId": "24775349",
    "mail": "picotietpicota@orange.fr",
    "distance": 38977,
    "latitude": 47.498032825446636,
    "telephone": "0241863427",
    "statusCompte": 2,
    "type": "EAJE",
    "nom": "Micro-crècheprivée Picoti et Picota, St Sylvain d'Anjou",
    "resultStructId": "709767",
    "omegaId": "0",
    "avip": false,
    "adresse": "5 chemin duclos dore 49480 verrieres",
    "details": {
      "dispo": {
        "allNonRenseigne": true
      }
    },
    "derniereModifDate": "19/11/2023",
    "dispo": false,
    "longitude": -0.4901402247050109,
    "ville": "enanjou",
    "cp": ""
  },
  {
    "resultId": "13037594",
    "mail": "multiaccueil.grainsdesoleil@gmail.com",
    "distance": 39795,
    "latitude": 47.51917916128481,
    "telephone": "0241768937",
    "statusCompte": 2,
    "type": "EAJE",
    "nom": "Multi-accueil\"Grains de Soleil\", Saint Sylvain d'Anjou",
    "resultStructId": "713602",
    "omegaId": "0",
    "avip": false,
    "adresse": "1 rue desbles d'or 49480 verrieres",
    "details": {
      "dispo": {
        "allNonRenseigne": true
      }
    },
    "derniereModifDate": "19/11/2023",
    "dispo": false,
    "longitude": -0.46875914744586294,
    "ville": "enanjou",
    "cp": ""
  },
  {
    "resultId": "13037207",
    "mail": "multiaccueil.petitpoucet@gmail.com",
    "distance": 41893,
    "latitude": 47.522543871750294,
    "telephone": "0241764690",
    "statusCompte": 2,
    "type": "EAJE",
    "nom": "Multi-accueil\"Petit Poucet\", Pellouailles les vignes",
    "resultStructId": "23817",
    "omegaId": "0",
    "avip": false,
    "adresse": "13 rue desvignes 49112 verrieres",
    "details": {
      "dispo": {
        "allNonRenseigne": true
      }
    },
    "derniereModifDate": "19/11/2023",
    "dispo": false,
    "longitude": -0.4384959073285132,
    "ville": "enanjou",
    "cp": ""
  },
  {
    "resultId": "30287106",
    "mail": "1001petitesmains@orange.fr",
    "distance": 46240,
    "latitude": 47.241110538239916,
    "telephone": "0241300501",
    "statusCompte": 2,
    "type": "EAJE",
    "nom": "Micro-crècheprivée 1001 petites mains,Chemillé-en-Anjou",
    "resultStructId": "712502",
    "omegaId": "0",
    "avip": false,
    "allNonRenseigne": false,
    "adresse": "4 alleekonrad adenauer 49120 chemille",
    "details": {
      "dispo": {
        "allNonRenseigne": true
      }
    },
    "derniereModifDate": "19/11/2023",
    "dispo": false,
    "longitude": -0.7101051515314909,
    "ville": "enanjou",
    "cp": ""
  },
  {
    "resultId": "40256029",
    "mail": "micro-creche-au-pays-des-reves@orange.fr",
    "distance": 46245,
    "latitude": 47.24104967424489,
    "telephone": "0241627796",
    "statusCompte": 2,
    "type": "EAJE",
    "nom": "Micro-crècheprivée Au Pays des Rêves, Chemillé-en-Anjou",
    "resultStructId": "709717",
    "omegaId": "0",
    "avip": false,
    "adresse": "6 alleekonrad adenauer 49120 chemille",
    "details": {
      "dispo": {
        "allNonRenseigne": true
      }
    },
    "derniereModifDate": "19/11/2023",
    "dispo": false,
    "longitude": -0.7101390660477512,
    "ville": "enanjou",
    "cp": ""
  },
  {
    "resultId": "12930903",
    "mail": "ma-calinous-pdl@vyv3.fr",
    "distance": 48589,
    "latitude": 47.21391698397926,
    "telephone": "0241303922",
    "statusCompte": 2,
    "type": "EAJE",
    "nom": "Multi-accueil\"Les Calinous\", Chemillé - Chemillé en Anjou",
    "resultStructId": "713015",
    "omegaId": "0",
    "avip": false,
    "adresse": "4 bisrue la chesnaie 49120 chemille",
    "details": {
      "dispo": {
        "allNonRenseigne": true
      }
    },
    "derniereModifDate": "19/11/2023",
    "dispo": false,
    "longitude": -0.7228037056532637,
    "ville": "enanjou",
    "cp": ""
  },
  {
    "resultId": "57948239",
    "mail": "contact@dansmacabane.fr",
    "distance": 58369,
    "latitude": 47.44595097044252,
    "telephone": "0672988581",
    "statusCompte": 2,
    "type": "EAJE",
    "nom": "Micro-crèchesprivées Dans ma Cabane 1, Beaufort en Anjou",
    "resultStructId": "709787",
    "omegaId": "0",
    "avip": false,
    "adresse": "22 rue deshauts champs 49250 beaufort",
    "details": {
      "dispo": {
        "allNonRenseigne": true
      }
    },
    "derniereModifDate": "19/11/2023",
    "dispo": false,
    "longitude": -0.24376703520258264,
    "ville": "enanjou",
    "cp": ""
  },
  {
    "resultId": "59872469",
    "mail": "contact@dansmacabane.fr",
    "distance": 58541,
    "latitude": 47.43951129787905,
    "telephone": "0672988581",
    "statusCompte": 2,
    "type": "EAJE",
    "nom": "Micro-crèchesprivées Dans ma Cabane 2, Beaufort en Anjou",
    "resultStructId": "709786",
    "omegaId": "0",
    "avip": false,
    "adresse": "14 route del'izenelle 49250 beaufort",
    "details": {
      "dispo": {
        "allNonRenseigne": true
      }
    },
    "derniereModifDate": "19/11/2023",
    "dispo": false,
    "longitude": -0.24468319711073766,
    "ville": "enanjou",
    "cp": ""
  },
  {
    "resultId": "12929484",
    "mail": "lesgaiminous@beaufortenanjou.fr",
    "distance": 60318,
    "latitude": 47.44037949351048,
    "telephone": "0241444431",
    "statusCompte": 2,
    "type": "EAJE",
    "nom": "Halte-garderieAFR \"Les Gaiminous\", Beaufort en Vallée",
    "resultStructId": "701448",
    "omegaId": "0",
    "avip": false,
    "adresse": "1 rue desdeportes 49250 beaufort",
    "details": {
      "dispo": {
        "allNonRenseigne": true
      }
    },
    "derniereModifDate": "19/11/2023",
    "dispo": false,
    "longitude": -0.2191919265895991,
    "ville": "enanjou",
    "cp": ""
  },
  {
    "resultId": "12950554",
    "mail": "crechefamiliale@association-galipette.org",
    "distance": 66130,
    "latitude": 47.54379778954025,
    "telephone": "0241892185",
    "statusCompte": 2,
    "type": "EAJE",
    "nom": "Crèchefamiliale associative \"La Galipette\" Baugé",
    "resultStructId": "688810",
    "omegaId": "0",
    "avip": false,
    "adresse": "8 bis ruede la croix verte 49150 bauge",
    "details": {
      "dispo": {
        "allNonRenseigne": true
      }
    },
    "derniereModifDate": "19/11/2023",
    "dispo": false,
    "longitude": -0.10457289074768139,
    "ville": "enanjou",
    "cp": ""
  },
  {
    "resultId": "12929613",
    "mail": "creche@association-galipette.org",
    "distance": 66130,
    "latitude": 47.54379778954025,
    "telephone": "0241897750",
    "statusCompte": 2,
    "type": "EAJE",
    "nom": "Multi-accueilla \"Galipette\", Baugé en Anjou",
    "resultStructId": "695501",
    "omegaId": "0",
    "avip": false,
    "adresse": "8 bis rue de la croixverte 49150 bauge",
    "details": {
      "dispo": {
        "allNonRenseigne": true
      }
    },
    "derniereModifDate": "19/11/2023",
    "dispo": false,
    "longitude": -0.10457289074768139,
    "ville": "enanjou",
    "cp": ""
  },
  {
    "resultId": "33514250",
    "mail": "hautscomme3pommes@yahoo.fr",
    "distance": 66357,
    "latitude": 47.54966755934381,
    "telephone": "0671991063",
    "statusCompte": 2,
    "type": "EAJE",
    "nom": "Micro-crècheprivée Hauts comme 3 pommes, Baugé en Anjou",
    "resultStructId": "709743",
    "omegaId": "0",
    "avip": false,
    "adresse": "10 avenuede la pree 49150 bauge",
    "details": {
      "dispo": {
        "allNonRenseigne": true
      }
    },
    "derniereModifDate": "19/11/2023",
    "dispo": false,
    "longitude": -0.10046800947088334,
    "ville": "enanjou",
    "cp": ""
  },
  {
    "resultId": "13016645",
    "mail": "multi-accueil@doue-en-anjou.fr",
    "distance": 70024,
    "latitude": 47.198959111337714,
    "telephone": "0241597698",
    "statusCompte": 2,
    "type": "EAJE",
    "nom": "Multi-accueilmunicipal de Doué-en-Anjou",
    "resultStructId": "639301",
    "omegaId": "0",
    "avip": false,
    "adresse": "4 rue pasteur 49700 doue",
    "details": {
      "dispo": {
        "allNonRenseigne": true
      }
    },
    "derniereModifDate": "19/11/2023",
    "dispo": false,
    "longitude": -0.2810753492708722,
    "ville": "enanjou",
    "cp": ""
  },
  {
    "resultId": "57188989",
    "mail": "mademande@fazill-home.fr",
    "distance": 149421,
    "latitude": 47.60225745506025,
    "telephone": "0786829796",
    "statusCompte": 2,
    "type": "EAJE",
    "nom": "Micro-crècheprivée Fazill'home, Vernd'Anjou",
    "resultStructId": "709727",
    "omegaId": "0",
    "avip": false,
    "dateProchaineDispo": "2023-11-22",
    "adresse": "9 rue detatsfield 49220 erdre",
    "details": {
      "dispo": {
        "allNonRenseigne": true
      }
    },
    "derniereModifDate": "19/11/2023",
    "dispo": true,
    "longitude": -0.8325270663973513,
    "ville": "enanjou",
    "cp": ""
  },
  {
    "resultId": "12928108",
    "mail": "contact@lesptitspieds.fr",
    "distance": 152722,
    "latitude": 47.56041053686627,
    "telephone": "0629600084",
    "statusCompte": 2,
    "type": "EAJE",
    "nom": "Micro-crècheprivée Les P'tits Pieds, Longuenée-en-Anjou",
    "resultStructId": "709721",
    "omegaId": "0",
    "avip": false,
    "adresse": "38 rue paulgauguin 49770 longuenee",
    "details": {
      "dispo": {
        "allNonRenseigne": true
      }
    },
    "derniereModifDate": "19/11/2023",
    "dispo": false,
    "longitude": -0.6807524689792825,
    "ville": "enanjou",
    "cp": ""
  },
  {
    "resultId": "33514250",
    "mail": "hautscomme3pommes@yahoo.fr",
    "distance": 156509,
    "latitude": 47.54966755934381,
    "telephone": "0671991063",
    "statusCompte": 2,
    "type": "EAJE",
    "nom": "Micro-crècheprivée Hauts comme 3 pommes, Baugé en Anjou",
    "resultStructId": "709743",
    "omegaId": "0",
    "avip": false,
    "adresse": "10 avenuede la pree 49150 bauge",
    "details": {
      "dispo": {
        "allNonRenseigne": true
      }
    },
    "derniereModifDate": "19/11/2023",
    "dispo": false,
    "longitude": -0.10046800947088334,
    "ville": "enanjou",
    "cp": ""
  },
  {
    "resultId": "13037207",
    "mail": "multiaccueil.petitpoucet@gmail.com",
    "distance": 156561,
    "latitude": 47.522543871750294,
    "telephone": "0241764690",
    "statusCompte": 2,
    "type": "EAJE",
    "nom": "Multi-accueil\"Petit Poucet\", Pellouailles les vignes",
    "resultStructId": "23817",
    "omegaId": "0",
    "avip": false,
    "adresse": "13 rue desvignes 49112 verrieres",
    "details": {
      "dispo": {
        "allNonRenseigne": true
      }
    },
    "derniereModifDate": "19/11/2023",
    "dispo": false,
    "longitude": -0.4384959073285132,
    "ville": "enanjou",
    "cp": ""
  },
  {
    "resultId": "24552604",
    "mail": "lacabanedescastors@gmail.com",
    "distance": 156789,
    "latitude": 47.52332826397502,
    "telephone": "0241951141",
    "statusCompte": 2,
    "type": "EAJE",
    "nom": "Micro-crècheprivée \"La Cabane des Castors\", La Meignanne",
    "resultStructId": "709762",
    "omegaId": "0",
    "avip": false,
    "adresse": "19 ruede la chenaie 49770 longuenee",
    "details": {
      "dispo": {
        "allNonRenseigne": true
      }
    },
    "derniereModifDate": "19/11/2023",
    "dispo": false,
    "longitude": -0.6729293981401675,
    "ville": "enanjou",
    "cp": ""
  },
  {
    "resultId": "13037594",
    "mail": "multiaccueil.grainsdesoleil@gmail.com",
    "distance": 156867,
    "latitude": 47.51917916128481,
    "telephone": "0241768937",
    "statusCompte": 2,
    "type": "EAJE",
    "nom": "Multi-accueil\"Grains de Soleil\", Saint Sylvain d'Anjou",
    "resultStructId": "713602",
    "omegaId": "0",
    "avip": false,
    "adresse": "1 rue desbles d'or 49480 verrieres",
    "details": {
      "dispo": {
        "allNonRenseigne": true
      }
    },
    "derniereModifDate": "19/11/2023",
    "dispo": false,
    "longitude": -0.46875914744586294,
    "ville": "enanjou",
    "cp": ""
  },
  {
    "resultId": "12950554",
    "mail": "crechefamiliale@association-galipette.org",
    "distance": 157090,
    "latitude": 47.54379778954025,
    "telephone": "0241892185",
    "statusCompte": 2,
    "type": "EAJE",
    "nom": "Crèchefamiliale associative \"La Galipette\" Baugé",
    "resultStructId": "688810",
    "omegaId": "0",
    "avip": false,
    "adresse": "8 bis ruede la croix verte 49150 bauge",
    "details": {
      "dispo": {
        "allNonRenseigne": true
      }
    },
    "derniereModifDate": "19/11/2023",
    "dispo": false,
    "longitude": -0.10457289074768139,
    "ville": "enanjou",
    "cp": ""
  },
  {
    "resultId": "12929613",
    "mail": "creche@association-galipette.org",
    "distance": 157090,
    "latitude": 47.54379778954025,
    "telephone": "0241897750",
    "statusCompte": 2,
    "type": "EAJE",
    "nom": "Multi-accueilla \"Galipette\", Baugé en Anjou",
    "resultStructId": "695501",
    "omegaId": "0",
    "avip": false,
    "adresse": "8 bis rue de la croixverte 49150 bauge",
    "details": {
      "dispo": {
        "allNonRenseigne": true
      }
    },
    "derniereModifDate": "19/11/2023",
    "dispo": false,
    "longitude": -0.10457289074768139,
    "ville": "enanjou",
    "cp": ""
  },
  {
    "resultId": "24775349",
    "mail": "picotietpicota@orange.fr",
    "distance": 159190,
    "latitude": 47.498032825446636,
    "telephone": "0241863427",
    "statusCompte": 2,
    "type": "EAJE",
    "nom": "Micro-crècheprivée Picoti et Picota, St Sylvain d'Anjou",
    "resultStructId": "709767",
    "omegaId": "0",
    "avip": false,
    "adresse": "5 chemin duclos dore 49480 verrieres",
    "details": {
      "dispo": {
        "allNonRenseigne": true
      }
    },
    "derniereModifDate": "19/11/2023",
    "dispo": false,
    "longitude": -0.4901402247050109,
    "ville": "enanjou",
    "cp": ""
  },
  {
    "resultId": "57823043",
    "mail": "marie@creche-poppins.fr",
    "distance": 159854,
    "latitude": 47.492031649951606,
    "telephone": "0632782428",
    "statusCompte": 2,
    "type": "EAJE",
    "nom": "Micro-crècheprivée Marie Poppins, St Sylvain d'Anjou",
    "resultStructId": "709738",
    "omegaId": "0",
    "avip": false,
    "adresse": "12 rue de lacharronnerie 49480 verrieres",
    "details": {
      "dispo": {
        "allNonRenseigne": true
      }
    },
    "derniereModifDate": "19/11/2023",
    "dispo": false,
    "longitude": -0.493618867924579,
    "ville": "enanjou",
    "cp": ""
  },
  {
    "resultId": "57948239",
    "mail": "contact@dansmacabane.fr",
    "distance": 166210,
    "latitude": 47.44595097044252,
    "telephone": "0672988581",
    "statusCompte": 2,
    "type": "EAJE",
    "nom": "Micro-crèchesprivées Dans ma Cabane 1, Beaufort en Anjou",
    "resultStructId": "709787",
    "omegaId": "0",
    "avip": false,
    "adresse": "22 rue deshauts champs 49250 beaufort",
    "details": {
      "dispo": {
        "allNonRenseigne": true
      }
    },
    "derniereModifDate": "19/11/2023",
    "dispo": false,
    "longitude": -0.24376703520258264,
    "ville": "enanjou",
    "cp": ""
  },
  {
    "resultId": "59872469",
    "mail": "contact@dansmacabane.fr",
    "distance": 166912,
    "latitude": 47.43951129787905,
    "telephone": "0672988581",
    "statusCompte": 2,
    "type": "EAJE",
    "nom": "Micro-crèchesprivées Dans ma Cabane 2, Beaufort en Anjou",
    "resultStructId": "709786",
    "omegaId": "0",
    "avip": false,
    "adresse": "14 route del'izenelle 49250 beaufort",
    "details": {
      "dispo": {
        "allNonRenseigne": true
      }
    },
    "derniereModifDate": "19/11/2023",
    "dispo": false,
    "longitude": -0.24468319711073766,
    "ville": "enanjou",
    "cp": ""
  },
  {
    "resultId": "12929484",
    "mail": "lesgaiminous@beaufortenanjou.fr",
    "distance": 167056,
    "latitude": 47.44037949351048,
    "telephone": "0241444431",
    "statusCompte": 2,
    "type": "EAJE",
    "nom": "Halte-garderieAFR \"Les Gaiminous\", Beaufort en Vallée",
    "resultStructId": "701448",
    "omegaId": "0",
    "avip": false,
    "adresse": "1 rue desdeportes 49250 beaufort",
    "details": {
      "dispo": {
        "allNonRenseigne": true
      }
    },
    "derniereModifDate": "19/11/2023",
    "dispo": false,
    "longitude": -0.2191919265895991,
    "ville": "enanjou",
    "cp": ""
  },
  {
    "resultId": "26377344",
    "mail": "crechedemelay@orange.fr",
    "distance": 184433,
    "latitude": 47.285711583583605,
    "telephone": "0241461851",
    "statusCompte": 2,
    "type": "EAJE",
    "nom": "Micro-crècheprivée Babychou, Melay",
    "resultStructId": "709723",
    "omegaId": "0",
    "avip": false,
    "adresse": "2 rue du haut des sources za dessources 49120 chemille",
    "details": {
      "dispo": {
        "allNonRenseigne": true
      }
    },
    "derniereModifDate": "19/11/2023",
    "dispo": false,
    "longitude": -0.848489419802517,
    "ville": "enanjou",
    "cp": ""
  },
  {
    "resultId": "30287106",
    "mail": "1001petitesmains@orange.fr",
    "distance": 188291,
    "latitude": 47.241110538239916,
    "telephone": "0241300501",
    "statusCompte": 2,
    "type": "EAJE",
    "nom": "Micro-crècheprivée 1001 petites mains,Chemillé-en-Anjou",
    "resultStructId": "712502",
    "omegaId": "0",
    "avip": false,
    "allNonRenseigne": false,
    "adresse": "4 alleekonrad adenauer 49120 chemille",
    "details": {
      "dispo": {
        "allNonRenseigne": true
      }
    },
    "derniereModifDate": "19/11/2023",
    "dispo": false,
    "longitude": -0.7101051515314909,
    "ville": "enanjou",
    "cp": ""
  },
  {
    "resultId": "40256029",
    "mail": "micro-creche-au-pays-des-reves@orange.fr",
    "distance": 188298,
    "latitude": 47.24104967424489,
    "telephone": "0241627796",
    "statusCompte": 2,
    "type": "EAJE",
    "nom": "Micro-crècheprivée Au Pays des Rêves, Chemillé-en-Anjou",
    "resultStructId": "709717",
    "omegaId": "0",
    "avip": false,
    "adresse": "6 alleekonrad adenauer 49120 chemille",
    "details": {
      "dispo": {
        "allNonRenseigne": true
      }
    },
    "derniereModifDate": "19/11/2023",
    "dispo": false,
    "longitude": -0.7101390660477512,
    "ville": "enanjou",
    "cp": ""
  },
  {
    "resultId": "12930903",
    "mail": "ma-calinous-pdl@vyv3.fr",
    "distance": 191380,
    "latitude": 47.21391698397926,
    "telephone": "0241303922",
    "statusCompte": 2,
    "type": "EAJE",
    "nom": "Multi-accueil\"Les Calinous\", Chemillé - Chemillé en Anjou",
    "resultStructId": "713015",
    "omegaId": "0",
    "avip": false,
    "adresse": "4 bisrue la chesnaie 49120 chemille",
    "details": {
      "dispo": {
        "allNonRenseigne": true
      }
    },
    "derniereModifDate": "19/11/2023",
    "dispo": false,
    "longitude": -0.7228037056532637,
    "ville": "enanjou",
    "cp": ""
  },
  {
    "resultId": "13016645",
    "mail": "multi-accueil@doue-en-anjou.fr",
    "distance": 193231,
    "latitude": 47.198959111337714,
    "telephone": "0241597698",
    "statusCompte": 2,
    "type": "EAJE",
    "nom": "Multi-accueilmunicipal de Doué-en-Anjou",
    "resultStructId": "639301",
    "omegaId": "0",
    "avip": false,
    "adresse": "4 rue pasteur 49700 doue",
    "details": {
      "dispo": {
        "allNonRenseigne": true
      }
    },
    "derniereModifDate": "19/11/2023",
    "dispo": false,
    "longitude": -0.2810753492708722,
    "ville": "enanjou",
    "cp": ""
  },
  {
    "resultId": "57188989",
    "mail": "mademande@fazill-home.fr",
    "distance": 11136,
    "latitude": 47.60225745506025,
    "telephone": "0786829796",
    "statusCompte": 2,
    "type": "EAJE",
    "nom": "Micro-crècheprivée Fazill'home, Vernd'Anjou",
    "resultStructId": "709727",
    "omegaId": "0",
    "avip": false,
    "dateProchaineDispo": "2023-11-22",
    "adresse": "9 rue detatsfield 49220 erdre",
    "details": {
      "dispo": {
        "allNonRenseigne": true
      }
    },
    "derniereModifDate": "19/11/2023",
    "dispo": true,
    "longitude": -0.8325270663973513,
    "ville": "enanjou",
    "cp": ""
  },
  {
    "resultId": "12928108",
    "mail": "contact@lesptitspieds.fr",
    "distance": 23235,
    "latitude": 47.56041053686627,
    "telephone": "0629600084",
    "statusCompte": 2,
    "type": "EAJE",
    "nom": "Micro-crècheprivée Les P'tits Pieds, Longuenée-en-Anjou",
    "resultStructId": "709721",
    "omegaId": "0",
    "avip": false,
    "adresse": "38 rue paulgauguin 49770 longuenee",
    "details": {
      "dispo": {
        "allNonRenseigne": true
      }
    },
    "derniereModifDate": "19/11/2023",
    "dispo": false,
    "longitude": -0.6807524689792825,
    "ville": "enanjou",
    "cp": ""
  },
  {
    "resultId": "24552604",
    "mail": "lacabanedescastors@gmail.com",
    "distance": 25175,
    "latitude": 47.52332826397502,
    "telephone": "0241951141",
    "statusCompte": 2,
    "type": "EAJE",
    "nom": "Micro-crècheprivée \"La Cabane des Castors\", La Meignanne",
    "resultStructId": "709762",
    "omegaId": "0",
    "avip": false,
    "adresse": "19 ruede la chenaie 49770 longuenee",
    "details": {
      "dispo": {
        "allNonRenseigne": true
      }
    },
    "derniereModifDate": "19/11/2023",
    "dispo": false,
    "longitude": -0.6729293981401675,
    "ville": "enanjou",
    "cp": ""
  },
  {
    "resultId": "26377344",
    "mail": "crechedemelay@orange.fr",
    "distance": 37899,
    "latitude": 47.285711583583605,
    "telephone": "0241461851",
    "statusCompte": 2,
    "type": "EAJE",
    "nom": "Micro-crècheprivée Babychou, Melay",
    "resultStructId": "709723",
    "omegaId": "0",
    "avip": false,
    "adresse": "2 rue du haut des sources za dessources 49120 chemille",
    "details": {
      "dispo": {
        "allNonRenseigne": true
      }
    },
    "derniereModifDate": "19/11/2023",
    "dispo": false,
    "longitude": -0.848489419802517,
    "ville": "enanjou",
    "cp": ""
  },
  {
    "resultId": "57823043",
    "mail": "marie@creche-poppins.fr",
    "distance": 38962,
    "latitude": 47.492031649951606,
    "telephone": "0632782428",
    "statusCompte": 2,
    "type": "EAJE",
    "nom": "Micro-crècheprivée Marie Poppins, St Sylvain d'Anjou",
    "resultStructId": "709738",
    "omegaId": "0",
    "avip": false,
    "adresse": "12 rue de lacharronnerie 49480 verrieres",
    "details": {
      "dispo": {
        "allNonRenseigne": true
      }
    },
    "derniereModifDate": "19/11/2023",
    "dispo": false,
    "longitude": -0.493618867924579,
    "ville": "enanjou",
    "cp": ""
  },
  {
    "resultId": "24775349",
    "mail": "picotietpicota@orange.fr",
    "distance": 38977,
    "latitude": 47.498032825446636,
    "telephone": "0241863427",
    "statusCompte": 2,
    "type": "EAJE",
    "nom": "Micro-crècheprivée Picoti et Picota, St Sylvain d'Anjou",
    "resultStructId": "709767",
    "omegaId": "0",
    "avip": false,
    "adresse": "5 chemin duclos dore 49480 verrieres",
    "details": {
      "dispo": {
        "allNonRenseigne": true
      }
    },
    "derniereModifDate": "19/11/2023",
    "dispo": false,
    "longitude": -0.4901402247050109,
    "ville": "enanjou",
    "cp": ""
  },
  {
    "resultId": "13037594",
    "mail": "multiaccueil.grainsdesoleil@gmail.com",
    "distance": 39795,
    "latitude": 47.51917916128481,
    "telephone": "0241768937",
    "statusCompte": 2,
    "type": "EAJE",
    "nom": "Multi-accueil\"Grains de Soleil\", Saint Sylvain d'Anjou",
    "resultStructId": "713602",
    "omegaId": "0",
    "avip": false,
    "adresse": "1 rue desbles d'or 49480 verrieres",
    "details": {
      "dispo": {
        "allNonRenseigne": true
      }
    },
    "derniereModifDate": "19/11/2023",
    "dispo": false,
    "longitude": -0.46875914744586294,
    "ville": "enanjou",
    "cp": ""
  },
  {
    "resultId": "13037207",
    "mail": "multiaccueil.petitpoucet@gmail.com",
    "distance": 41893,
    "latitude": 47.522543871750294,
    "telephone": "0241764690",
    "statusCompte": 2,
    "type": "EAJE",
    "nom": "Multi-accueil\"Petit Poucet\", Pellouailles les vignes",
    "resultStructId": "23817",
    "omegaId": "0",
    "avip": false,
    "adresse": "13 rue desvignes 49112 verrieres",
    "details": {
      "dispo": {
        "allNonRenseigne": true
      }
    },
    "derniereModifDate": "19/11/2023",
    "dispo": false,
    "longitude": -0.4384959073285132,
    "ville": "enanjou",
    "cp": ""
  },
  {
    "resultId": "30287106",
    "mail": "1001petitesmains@orange.fr",
    "distance": 46240,
    "latitude": 47.241110538239916,
    "telephone": "0241300501",
    "statusCompte": 2,
    "type": "EAJE",
    "nom": "Micro-crècheprivée 1001 petites mains,Chemillé-en-Anjou",
    "resultStructId": "712502",
    "omegaId": "0",
    "avip": false,
    "allNonRenseigne": false,
    "adresse": "4 alleekonrad adenauer 49120 chemille",
    "details": {
      "dispo": {
        "allNonRenseigne": true
      }
    },
    "derniereModifDate": "19/11/2023",
    "dispo": false,
    "longitude": -0.7101051515314909,
    "ville": "enanjou",
    "cp": ""
  },
  {
    "resultId": "40256029",
    "mail": "micro-creche-au-pays-des-reves@orange.fr",
    "distance": 46245,
    "latitude": 47.24104967424489,
    "telephone": "0241627796",
    "statusCompte": 2,
    "type": "EAJE",
    "nom": "Micro-crècheprivée Au Pays des Rêves, Chemillé-en-Anjou",
    "resultStructId": "709717",
    "omegaId": "0",
    "avip": false,
    "adresse": "6 alleekonrad adenauer 49120 chemille",
    "details": {
      "dispo": {
        "allNonRenseigne": true
      }
    },
    "derniereModifDate": "19/11/2023",
    "dispo": false,
    "longitude": -0.7101390660477512,
    "ville": "enanjou",
    "cp": ""
  },
  {
    "resultId": "12930903",
    "mail": "ma-calinous-pdl@vyv3.fr",
    "distance": 48589,
    "latitude": 47.21391698397926,
    "telephone": "0241303922",
    "statusCompte": 2,
    "type": "EAJE",
    "nom": "Multi-accueil\"Les Calinous\", Chemillé - Chemillé en Anjou",
    "resultStructId": "713015",
    "omegaId": "0",
    "avip": false,
    "adresse": "4 bisrue la chesnaie 49120 chemille",
    "details": {
      "dispo": {
        "allNonRenseigne": true
      }
    },
    "derniereModifDate": "19/11/2023",
    "dispo": false,
    "longitude": -0.7228037056532637,
    "ville": "enanjou",
    "cp": ""
  },
  {
    "resultId": "57948239",
    "mail": "contact@dansmacabane.fr",
    "distance": 58369,
    "latitude": 47.44595097044252,
    "telephone": "0672988581",
    "statusCompte": 2,
    "type": "EAJE",
    "nom": "Micro-crèchesprivées Dans ma Cabane 1, Beaufort en Anjou",
    "resultStructId": "709787",
    "omegaId": "0",
    "avip": false,
    "adresse": "22 rue deshauts champs 49250 beaufort",
    "details": {
      "dispo": {
        "allNonRenseigne": true
      }
    },
    "derniereModifDate": "19/11/2023",
    "dispo": false,
    "longitude": -0.24376703520258264,
    "ville": "enanjou",
    "cp": ""
  },
  {
    "resultId": "59872469",
    "mail": "contact@dansmacabane.fr",
    "distance": 58541,
    "latitude": 47.43951129787905,
    "telephone": "0672988581",
    "statusCompte": 2,
    "type": "EAJE",
    "nom": "Micro-crèchesprivées Dans ma Cabane 2, Beaufort en Anjou",
    "resultStructId": "709786",
    "omegaId": "0",
    "avip": false,
    "adresse": "14 route del'izenelle 49250 beaufort",
    "details": {
      "dispo": {
        "allNonRenseigne": true
      }
    },
    "derniereModifDate": "19/11/2023",
    "dispo": false,
    "longitude": -0.24468319711073766,
    "ville": "enanjou",
    "cp": ""
  },
  {
    "resultId": "12929484",
    "mail": "lesgaiminous@beaufortenanjou.fr",
    "distance": 60318,
    "latitude": 47.44037949351048,
    "telephone": "0241444431",
    "statusCompte": 2,
    "type": "EAJE",
    "nom": "Halte-garderieAFR \"Les Gaiminous\", Beaufort en Vallée",
    "resultStructId": "701448",
    "omegaId": "0",
    "avip": false,
    "adresse": "1 rue desdeportes 49250 beaufort",
    "details": {
      "dispo": {
        "allNonRenseigne": true
      }
    },
    "derniereModifDate": "19/11/2023",
    "dispo": false,
    "longitude": -0.2191919265895991,
    "ville": "enanjou",
    "cp": ""
  },
  {
    "resultId": "12950554",
    "mail": "crechefamiliale@association-galipette.org",
    "distance": 66130,
    "latitude": 47.54379778954025,
    "telephone": "0241892185",
    "statusCompte": 2,
    "type": "EAJE",
    "nom": "Crèchefamiliale associative \"La Galipette\" Baugé",
    "resultStructId": "688810",
    "omegaId": "0",
    "avip": false,
    "adresse": "8 bis ruede la croix verte 49150 bauge",
    "details": {
      "dispo": {
        "allNonRenseigne": true
      }
    },
    "derniereModifDate": "19/11/2023",
    "dispo": false,
    "longitude": -0.10457289074768139,
    "ville": "enanjou",
    "cp": ""
  },
  {
    "resultId": "12929613",
    "mail": "creche@association-galipette.org",
    "distance": 66130,
    "latitude": 47.54379778954025,
    "telephone": "0241897750",
    "statusCompte": 2,
    "type": "EAJE",
    "nom": "Multi-accueilla \"Galipette\", Baugé en Anjou",
    "resultStructId": "695501",
    "omegaId": "0",
    "avip": false,
    "adresse": "8 bis rue de la croixverte 49150 bauge",
    "details": {
      "dispo": {
        "allNonRenseigne": true
      }
    },
    "derniereModifDate": "19/11/2023",
    "dispo": false,
    "longitude": -0.10457289074768139,
    "ville": "enanjou",
    "cp": ""
  },
  {
    "resultId": "33514250",
    "mail": "hautscomme3pommes@yahoo.fr",
    "distance": 66357,
    "latitude": 47.54966755934381,
    "telephone": "0671991063",
    "statusCompte": 2,
    "type": "EAJE",
    "nom": "Micro-crècheprivée Hauts comme 3 pommes, Baugé en Anjou",
    "resultStructId": "709743",
    "omegaId": "0",
    "avip": false,
    "adresse": "10 avenuede la pree 49150 bauge",
    "details": {
      "dispo": {
        "allNonRenseigne": true
      }
    },
    "derniereModifDate": "19/11/2023",
    "dispo": false,
    "longitude": -0.10046800947088334,
    "ville": "enanjou",
    "cp": ""
  },
  {
    "resultId": "13016645",
    "mail": "multi-accueil@doue-en-anjou.fr",
    "distance": 70024,
    "latitude": 47.198959111337714,
    "telephone": "0241597698",
    "statusCompte": 2,
    "type": "EAJE",
    "nom": "Multi-accueilmunicipal de Doué-en-Anjou",
    "resultStructId": "639301",
    "omegaId": "0",
    "avip": false,
    "adresse": "4 rue pasteur 49700 doue",
    "details": {
      "dispo": {
        "allNonRenseigne": true
      }
    },
    "derniereModifDate": "19/11/2023",
    "dispo": false,
    "longitude": -0.2810753492708722,
    "ville": "enanjou",
    "cp": ""
  }
]