[
  {
    "resultId": "12637876",
    "mail": "a.metz@ville-fayence.fr",
    "distance": 166267,
    "latitude": 43.62335134665821,
    "telephone": "0494762843",
    "statusCompte": 2,
    "type": "EAJE",
    "nom": "LEGRAND JARDIN",
    "resultStructId": "15300",
    "omegaId": "0",
    "avip": false,
    "adresse": "38 ancienne voie ferree",
    "details": {
      "dispo": {
        "allNonRenseigne": true
      }
    },
    "derniereModifDate": "19/11/2023",
    "dispo": false,
    "longitude": 6.688350019707127,
    "ville": "fayence",
    "cp": "83440"
  },
  {
    "resultId": "12637876",
    "mail": "a.metz@ville-fayence.fr",
    "distance": 256183,
    "latitude": 43.62335134665821,
    "telephone": "0494762843",
    "statusCompte": 2,
    "type": "EAJE",
    "nom": "LEGRAND JARDIN",
    "resultStructId": "15300",
    "omegaId": "0",
    "avip": false,
    "adresse": "38 ancienne voie ferree",
    "details": {
      "dispo": {
        "allNonRenseigne": true
      }
    },
    "derniereModifDate": "19/11/2023",
    "dispo": false,
    "longitude": 6.688350019707127,
    "ville": "fayence",
    "cp": "83440"
  },
  {
    "resultId": "12637876",
    "mail": "a.metz@ville-fayence.fr",
    "distance": 62449,
    "latitude": 43.62335134665821,
    "telephone": "0494762843",
    "statusCompte": 2,
    "type": "EAJE",
    "nom": "LEGRAND JARDIN",
    "resultStructId": "15300",
    "omegaId": "0",
    "avip": false,
    "adresse": "38 ancienne voie ferree",
    "details": {
      "dispo": {
        "allNonRenseigne": true
      }
    },
    "derniereModifDate": "19/11/2023",
    "dispo": false,
    "longitude": 6.688350019707127,
    "ville": "fayence",
    "cp": "83440"
  }
]