[
  {
    "resultId": "12543835",
    "mail": "",
    "distance": 152884,
    "latitude": 49.170381752063676,
    "telephone": "0134675360",
    "statusCompte": 2,
    "type": "EAJE",
    "nom": "Crèchecollective - Haravilliers",
    "resultStructId": "1428",
    "omegaId": "0",
    "avip": false,
    "adresse": "9 rue de la mairie",
    "details": {
      "dispo": {
        "allNonRenseigne": true
      }
    },
    "derniereModifDate": "19/11/2023",
    "dispo": false,
    "longitude": 2.0390043935327786,
    "ville": "haravilliers",
    "cp": "95640"
  },
  {
    "resultId": "12543835",
    "mail": "",
    "distance": 188199,
    "latitude": 49.170381752063676,
    "telephone": "0134675360",
    "statusCompte": 2,
    "type": "EAJE",
    "nom": "Crèchecollective - Haravilliers",
    "resultStructId": "1428",
    "omegaId": "0",
    "avip": false,
    "adresse": "9 rue de la mairie",
    "details": {
      "dispo": {
        "allNonRenseigne": true
      }
    },
    "derniereModifDate": "19/11/2023",
    "dispo": false,
    "longitude": 2.0390043935327786,
    "ville": "haravilliers",
    "cp": "95640"
  }
]