[
  {
    "resultId": "12777170",
    "mail": "lespetitescanailles0703@orange.fr",
    "distance": 142289,
    "latitude": 47.89157614864119,
    "telephone": "0238948354",
    "statusCompte": 2,
    "type": "EAJE",
    "nom": "MultiAccueil \"les Petites Canailles\" - LORRIS",
    "resultStructId": "586003",
    "omegaId": "0",
    "avip": false,
    "adresse": "1 rue del'abzoue",
    "details": {
      "dispo": {
        "allNonRenseigne": true
      }
    },
    "derniereModifDate": "19/11/2023",
    "dispo": false,
    "longitude": 2.5164630336123,
    "ville": "lorris",
    "cp": "45260"
  },
  {
    "resultId": "12777170",
    "mail": "lespetitescanailles0703@orange.fr",
    "distance": 117037,
    "latitude": 47.89157614864119,
    "telephone": "0238948354",
    "statusCompte": 2,
    "type": "EAJE",
    "nom": "MultiAccueil \"les Petites Canailles\" - LORRIS",
    "resultStructId": "586003",
    "omegaId": "0",
    "avip": false,
    "adresse": "1 rue del'abzoue",
    "details": {
      "dispo": {
        "allNonRenseigne": true
      }
    },
    "derniereModifDate": "19/11/2023",
    "dispo": false,
    "longitude": 2.5164630336123,
    "ville": "lorris",
    "cp": "45260"
  }
]