[
  {
    "resultId": "12872724",
    "mail": "multiaccueilnerac@albretcommunaute.fr",
    "distance": 51636,
    "latitude": 44.13176070083812,
    "telephone": "0553653534",
    "statusCompte": 2,
    "type": "EAJE",
    "nom": "CrècheHalte-garderie \"Comptine\"",
    "resultStructId": "9106",
    "omegaId": "0",
    "avip": false,
    "adresse": "10 boulevard alfred",
    "details": {
      "dispo": {
        "allNonRenseigne": true
      }
    },
    "derniereModifDate": "19/11/2023",
    "dispo": false,
    "longitude": 0.3369614456509603,
    "ville": "nerac",
    "cp": "47600"
  }
]