[
  {
    "resultId": "57275844",
    "mail": "3ptitstours@orange.fr",
    "distance": 37601,
    "latitude": 47.34648739631725,
    "telephone": "0240965133",
    "statusCompte": 2,
    "type": "EAJE",
    "nom": "3P'tits Tours",
    "resultStructId": "673903",
    "omegaId": "0",
    "avip": false,
    "adresse": "171 rue de la loire",
    "details": {
      "dispo": {
        "allNonRenseigne": true
      }
    },
    "derniereModifDate": "19/11/2023",
    "dispo": false,
    "longitude": -1.284517389822762,
    "ville": "oudon",
    "cp": "44521"
  },
  {
    "resultId": "57275844",
    "mail": "3ptitstours@orange.fr",
    "distance": 185004,
    "latitude": 47.34648739631725,
    "telephone": "0240965133",
    "statusCompte": 2,
    "type": "EAJE",
    "nom": "3P'tits Tours",
    "resultStructId": "673903",
    "omegaId": "0",
    "avip": false,
    "adresse": "171 rue de la loire",
    "details": {
      "dispo": {
        "allNonRenseigne": true
      }
    },
    "derniereModifDate": "19/11/2023",
    "dispo": false,
    "longitude": -1.284517389822762,
    "ville": "oudon",
    "cp": "44521"
  },
  {
    "resultId": "57275844",
    "mail": "3ptitstours@orange.fr",
    "distance": 37601,
    "latitude": 47.34648739631725,
    "telephone": "0240965133",
    "statusCompte": 2,
    "type": "EAJE",
    "nom": "3P'tits Tours",
    "resultStructId": "673903",
    "omegaId": "0",
    "avip": false,
    "adresse": "171 rue de la loire",
    "details": {
      "dispo": {
        "allNonRenseigne": true
      }
    },
    "derniereModifDate": "19/11/2023",
    "dispo": false,
    "longitude": -1.284517389822762,
    "ville": "oudon",
    "cp": "44521"
  }
]