[
  {
    "resultId": "12835951",
    "mail": "opeera.86@gmail.com",
    "distance": 98748,
    "latitude": 46.81113554007792,
    "telephone": "0549935555",
    "statusCompte": 2,
    "type": "EAJE",
    "nom": "Multi-AccueilLa Flûte enchantée",
    "resultStructId": "457802",
    "omegaId": "0",
    "avip": false,
    "adresse": "2 allee des halles 86140",
    "details": {
      "dispo": {
        "allNonRenseigne": true
      }
    },
    "derniereModifDate": "19/11/2023",
    "dispo": false,
    "longitude": 0.41272989940254184,
    "ville": "scorbeclairvaux",
    "cp": ""
  },
  {
    "resultId": "12835951",
    "mail": "opeera.86@gmail.com",
    "distance": 138016,
    "latitude": 46.81113554007792,
    "telephone": "0549935555",
    "statusCompte": 2,
    "type": "EAJE",
    "nom": "Multi-AccueilLa Flûte enchantée",
    "resultStructId": "457802",
    "omegaId": "0",
    "avip": false,
    "adresse": "2 allee des halles 86140",
    "details": {
      "dispo": {
        "allNonRenseigne": true
      }
    },
    "derniereModifDate": "19/11/2023",
    "dispo": false,
    "longitude": 0.41272989940254184,
    "ville": "scorbeclairvaux",
    "cp": ""
  },
  {
    "resultId": "12835951",
    "mail": "opeera.86@gmail.com",
    "distance": 138016,
    "latitude": 46.81113554007792,
    "telephone": "0549935555",
    "statusCompte": 2,
    "type": "EAJE",
    "nom": "Multi-AccueilLa Flûte enchantée",
    "resultStructId": "457802",
    "omegaId": "0",
    "avip": false,
    "adresse": "2 allee des halles 86140",
    "details": {
      "dispo": {
        "allNonRenseigne": true
      }
    },
    "derniereModifDate": "19/11/2023",
    "dispo": false,
    "longitude": 0.41272989940254184,
    "ville": "scorbeclairvaux",
    "cp": ""
  }
]