[
  {
    "resultId": "21445694",
    "mail": "lilebleue@lamut.fr",
    "distance": 119395,
    "latitude": 43.202847934351894,
    "telephone": "0494332105",
    "statusCompte": 2,
    "type": "EAJE",
    "nom": "L'ﾃ四eBleue",
    "resultStructId": "706826",
    "omegaId": "0",
    "avip": false,
    "adresse": "537 avenue de valaury 83210",
    "details": {
      "dispo": {
        "allNonRenseigne": true
      }
    },
    "derniereModifDate": "19/11/2023",
    "dispo": false,
    "longitude": 6.0198595859448725,
    "ville": "solliestoucas",
    "cp": ""
  },
  {
    "resultId": "21445694",
    "mail": "lilebleue@lamut.fr",
    "distance": 278097,
    "latitude": 43.202847934351894,
    "telephone": "0494332105",
    "statusCompte": 2,
    "type": "EAJE",
    "nom": "L'ﾃ四eBleue",
    "resultStructId": "706826",
    "omegaId": "0",
    "avip": false,
    "adresse": "537 avenue de valaury 83210",
    "details": {
      "dispo": {
        "allNonRenseigne": true
      }
    },
    "derniereModifDate": "19/11/2023",
    "dispo": false,
    "longitude": 6.0198595859448725,
    "ville": "solliestoucas",
    "cp": ""
  },
  {
    "resultId": "21445694",
    "mail": "lilebleue@lamut.fr",
    "distance": 177065,
    "latitude": 43.202847934351894,
    "telephone": "0494332105",
    "statusCompte": 2,
    "type": "EAJE",
    "nom": "L'ﾃ四eBleue",
    "resultStructId": "706826",
    "omegaId": "0",
    "avip": false,
    "adresse": "537 avenue de valaury 83210",
    "details": {
      "dispo": {
        "allNonRenseigne": true
      }
    },
    "derniereModifDate": "19/11/2023",
    "dispo": false,
    "longitude": 6.0198595859448725,
    "ville": "solliestoucas",
    "cp": ""
  },
  {
    "resultId": "21445694",
    "mail": "lilebleue@lamut.fr",
    "distance": 83899,
    "latitude": 43.202847934351894,
    "telephone": "0494332105",
    "statusCompte": 2,
    "type": "EAJE",
    "nom": "L'ﾃ四eBleue",
    "resultStructId": "706826",
    "omegaId": "0",
    "avip": false,
    "adresse": "537 avenue de valaury 83210",
    "details": {
      "dispo": {
        "allNonRenseigne": true
      }
    },
    "derniereModifDate": "19/11/2023",
    "dispo": false,
    "longitude": 6.0198595859448725,
    "ville": "solliestoucas",
    "cp": ""
  }
]