[
  {
    "resultId": "60367581",
    "mail": "lpltiffauges@gmail.com",
    "distance": 68178,
    "latitude": 47.00843498080721,
    "telephone": "0676798972",
    "statusCompte": 2,
    "type": "EAJE",
    "nom": "Microcrèche Les P'tites Lucioles",
    "resultStructId": "709807",
    "omegaId": "0",
    "avip": false,
    "adresse": "7 impasse des jardins",
    "details": {
      "dispo": {
        "allNonRenseigne": true
      }
    },
    "derniereModifDate": "19/11/2023",
    "dispo": false,
    "longitude": -1.1143636590470702,
    "ville": "tiffauges",
    "cp": "85130"
  },
  {
    "resultId": "60367581",
    "mail": "lpltiffauges@gmail.com",
    "distance": 68178,
    "latitude": 47.00843498080721,
    "telephone": "0676798972",
    "statusCompte": 2,
    "type": "EAJE",
    "nom": "Microcrèche Les P'tites Lucioles",
    "resultStructId": "709807",
    "omegaId": "0",
    "avip": false,
    "adresse": "7 impasse des jardins",
    "details": {
      "dispo": {
        "allNonRenseigne": true
      }
    },
    "derniereModifDate": "19/11/2023",
    "dispo": false,
    "longitude": -1.1143636590470702,
    "ville": "tiffauges",
    "cp": "85130"
  }
]