[
  {
    "resultId": "13017333",
    "mail": "creche@laligue10.org",
    "distance": 112738,
    "latitude": 48.21808322642423,
    "telephone": "0325439342",
    "statusCompte": 2,
    "type": "EAJE",
    "nom": "Liguede l'enseignement service crèche LES QUEN'OTHE",
    "resultStructId": "689401",
    "omegaId": "0",
    "avip": false,
    "adresse": "8 rue duparc 10160 aix",
    "details": {
      "dispo": {
        "allNonRenseigne": true
      }
    },
    "derniereModifDate": "19/11/2023",
    "dispo": false,
    "longitude": 3.728953437391619,
    "ville": "villemaurpalis",
    "cp": ""
  },
  {
    "resultId": "13017333",
    "mail": "creche@laligue10.org",
    "distance": 82876,
    "latitude": 48.21808322642423,
    "telephone": "0325439342",
    "statusCompte": 2,
    "type": "EAJE",
    "nom": "Liguede l'enseignement service crèche LES QUEN'OTHE",
    "resultStructId": "689401",
    "omegaId": "0",
    "avip": false,
    "adresse": "8 rue duparc 10160 aix",
    "details": {
      "dispo": {
        "allNonRenseigne": true
      }
    },
    "derniereModifDate": "19/11/2023",
    "dispo": false,
    "longitude": 3.728953437391619,
    "ville": "villemaurpalis",
    "cp": ""
  }
]